forthic/__init__.py
forthic/global_module.py
forthic/interfaces.py
forthic/interpreter.py
forthic/module.py
forthic/profile.py
forthic/tokenizer.py
forthic/tokens.py
forthic/modules/__init__.py
forthic/modules/airtable_module.py
forthic/modules/alation_module.py
forthic/modules/cache_module.py
forthic/modules/confluence_module.py
forthic/modules/datasets_module.py
forthic/modules/excel_module.py
forthic/modules/gdoc_module.py
forthic/modules/gsheet_module.py
forthic/modules/html_module.py
forthic/modules/intake_module.py
forthic/modules/isoweek_module.py
forthic/modules/jinja_module.py
forthic/modules/jira_module.py
forthic/modules/org_module.py
forthic/modules/stats_module.py
forthic/modules/svg_module.py
forthic/modules/ui_module.py
forthic/modules/wiki_status_module.py
forthic/utils/__init__.py
forthic/utils/creds.py
forthic/utils/errors.py
forthic_lang-4.0.0.dist-info/LICENSE
forthic_lang-4.0.0.dist-info/WHEEL
forthic_lang-4.0.0.dist-info/METADATA
forthic_lang-4.0.0.dist-info/RECORD
