Metadata-Version: 2.1
Name: forthic-lang
Version: 4.0.0
Summary: A stack-based language for concisely building tweakable apps
Author-email: Rino Jose <rjose@forthix.com>
Requires-Dist: urllib3
Requires-Dist: pytz
Requires-Dist: cryptography
Requires-Dist: python-dateutil
Requires-Dist: requests-oauthlib
Requires-Dist: Jinja2
Requires-Dist: Markdown
Project-URL: Home, https://github.com/linkedin/forthic
